para/__init__.py
para/__main__.py
para/client.py
para/conversation_panel.py
para/messages.py
para/para.abi3.so
para/poller.py
para_sdk-0.25.1.dist-info/METADATA
para_sdk-0.25.1.dist-info/WHEEL
para_sdk-0.25.1.dist-info/RECORD
