Metadata-Version: 2.4
Name: para-sdk
Version: 0.25.1
Requires-Dist: python-mimeparse
Requires-Dist: panel
Requires-Dist: pydeck
Requires-Dist: ipython
